{
	"groups": [
		{
			"keys": "bg_jpg,egret_icon_png,description_json,ctm_jpg,天鹅湖-柴可夫斯基 - 新雅室内乐_mp3",
			"name": "preload"
		}
	],
	"resources": [
		{
			"url": "assets/bg.jpg",
			"type": "image",
			"name": "bg_jpg"
		},
		{
			"url": "assets/egret_icon.png",
			"type": "image",
			"name": "egret_icon_png"
		},
		{
			"url": "config/description.json",
			"type": "json",
			"name": "description_json"
		},
		{
			"url": "assets/ctm.jpg",
			"type": "image",
			"name": "ctm_jpg",
			"scale9grid": "195,106,519,503"
		},
		{
			"url": "assets/天鹅湖-柴可夫斯基 - 新雅室内乐.mp3",
			"type": "sound",
			"name": "天鹅湖-柴可夫斯基 - 新雅室内乐_mp3"
		}
	]
}